mail_framework/__init__.py
mail_framework/sendmail.py
sanjumailgenerator3-0.0.3.dist-info/LICENSE.txt
sanjumailgenerator3-0.0.3.dist-info/METADATA
sanjumailgenerator3-0.0.3.dist-info/WHEEL
sanjumailgenerator3-0.0.3.dist-info/top_level.txt
sanjumailgenerator3-0.0.3.dist-info/RECORD
