Metadata-Version: 2.1
Name: sanjumailgenerator3
Version: 0.0.3
Summary: A script to send automated mails.
Home-page: 
Author: Sanooj Babu
Author-email: sanooj.kakkoth@onebillsoftware.com
License: MIT
Keywords: mail
Classifier: Development Status :: 5 - Production/Stable
Classifier: Intended Audience :: Education
Classifier: Operating System :: OS Independent
Classifier: License :: OSI Approved :: MIT License
Classifier: Programming Language :: Python :: 3
License-File: LICENSE.txt
